temper/__init__.py
temper/temper.py
sudoistemper-0.1.0.dist-info/entry_points.txt
sudoistemper-0.1.0.dist-info/LICENSE
sudoistemper-0.1.0.dist-info/WHEEL
sudoistemper-0.1.0.dist-info/METADATA
sudoistemper-0.1.0.dist-info/RECORD
