Metadata-Version: 2.1
Name: sudoistemper
Version: 0.1.0
Summary: 
Author: urwen
Requires-Python: >=3.7,<4.0
Classifier: Programming Language :: Python :: 3
Classifier: Programming Language :: Python :: 3.7
Classifier: Programming Language :: Python :: 3.8
Requires-Dist: pyserial (>=3.4,<4.0)
